slot_attention_pytorch/__init__.py
slot_attention_pytorch/config/slot_attention-clevr.yaml
slot_attention_pytorch/config/slot_attention.yaml
slot_attention_pytorch/encoder_decoder.py
slot_attention_pytorch/model.py
slot_attention_pytorch/nn_utils.py
slot_attention_pytorch/paths.py
slot_attention_pytorch/positional_embedding.py
slot_attention_pytorch/shared/__init__.py
slot_attention_pytorch/shared/encoder_decoder.py
slot_attention_pytorch/shared/sequential_cnn.py
slot_attention_pytorch/shared/unet.py
slot_attention_pytorch/slot_attention_module.py
slot_attention_pytorch-0.1.0.dist-info/LICENSE
slot_attention_pytorch-0.1.0.dist-info/WHEEL
slot_attention_pytorch-0.1.0.dist-info/METADATA
slot_attention_pytorch-0.1.0.dist-info/RECORD
