Metadata-Version: 2.1
Name: slot-attention-pytorch
Version: 0.1.0
Summary: Pytorch slot-attention implementation of Slot Attention
Author: mikedev
Author-email: mik3dev@gmail.com
Requires-Python: >=3.9,<4.0
Classifier: Programming Language :: Python :: 3
Classifier: Programming Language :: Python :: 3.10
Classifier: Programming Language :: Python :: 3.9
Requires-Dist: hydra-core (>=1.2.0,<2.0.0)
Requires-Dist: path (>=16.4.0,<17.0.0)
Requires-Dist: torch (>=1.12.0,<2.0.0)
